cba_battle_advance/__init__.py
cba_battle_advance-1.dist-info/licenses/LICENSE
cba_battle_advance-1.dist-info/METADATA
cba_battle_advance-1.dist-info/WHEEL
cba_battle_advance-1.dist-info/top_level.txt
cba_battle_advance-1.dist-info/RECORD
