Metadata-Version: 2.4
Name: cba-battle-advance
Version: 1
Summary: cba
Author-email: unnamed7353 <unnamed7353@gmail.com>
Keywords: cba,hess
Classifier: Programming Language :: Python :: 3
Classifier: License :: OSI Approved :: MIT License
Classifier: Operating System :: OS Independent
License-File: LICENSE
Dynamic: license-file
